{
  "1": {
    "number": 1,
    "name": "Bulbasaur",
    "type": [
      "Grass",
      "Poison"
    ],
    "evolution": [
      2,
      3
    ]
  },
  "2": {
    "number": 2,
    "name": "Ivysaur",
    "type": [
      "Grass",
      "Poison"
    ],
    "evolution": [
      3
    ],
    "previous": 1
  },
  "3": {
    "number": 3,
    "name": "Venusaur",
    "type": [
      "Grass",
      "Poison"
    ],
    "previous": 2
  },
  "4": {
    "number": 4,
    "name": "Charmander",
    "type": [
      "Fire"
    ],
    "evolution": [
      4,
      5
    ]
  },
  "5": {
    "number": 5,
    "name": "Charmeleon",
    "type": [
      "Fire"
    ],
    "evolution": [
      5
    ],
    "previous": 4
  },
  "6": {
    "number": 6,
    "name": "Charizard",
    "type": [
      "Fire",
      "Flying"
    ],
    "previous": 5
  },
  "7": {
    "number": 7,
    "name": "Squirtle",
    "type": [
      "Water"
    ],
    "evolution": [
      8,
      9
    ]
  },
  "8": {
    "number": 8,
    "name": "Wartortle",
    "type": [
      "Water"
    ],
    "evolution": [
      9
    ],
    "previous": 7
  },
  "9": {
    "number": 9,
    "name": "Blastoise",
    "type": [
      "Water"
    ],
    "previous": 8
  },
  "10": {
    "number": 10,
    "name": "Caterpie",
    "type": [
      "Bug"
    ],
    "evolution": [
      11,
      12
    ]
  },
  "11": {
    "number": 11,
    "name": "Metapod",
    "type": [
      "Bug"
    ],
    "evolution": [
      12
    ],
    "previous": 10
  },
  "12": {
    "number": 12,
    "name": "Butterfree",
    "type": [
      "Bug",
      "Flying"
    ],
    "previous": 11
  },
  "13": {
    "number": 13,
    "name": "Weedle",
    "type": [
      "Bug",
      "Poison"
    ],
    "evolution": [
      14,
      15
    ]
  },
  "14": {
    "number": 14,
    "name": "Kakuna",
    "type": [
      "Bug",
      "Poison"
    ],
    "evolution": [
      15
    ],
    "previous": 13
  },
  "15": {
    "number": 15,
    "name": "Beedrill",
    "type": [
      "Bug",
      "Poison"
    ],
    "previous": 14
  },
  "16": {
    "number": 16,
    "name": "Pidgey",
    "type": [
      "Normal",
      "Flying"
    ],
    "evolution": [
      17,
      18
    ]
  },
  "17": {
    "number": 17,
    "name": "Pidgeotto",
    "type": [
      "Normal",
      "Flying"
    ],
    "evolution": [
      18
    ],
    "previous": 16
  },
  "18": {
    "number": 18,
    "name": "Pidgeot",
    "type": [
      "Normal",
      "Flying"
    ],
    "previous": 17
  },
  "19": {
    "number": 19,
    "name": "Rattata",
    "type": [
      "Normal"
    ],
    "evolution": [
      20
    ]
  },
  "20": {
    "number": 20,
    "name": "Raticate",
    "type": [
      "Normal"
    ],
    "previous": 19
  },
  "21": {
    "number": 21,
    "name": "Spearow",
    "type": [
      "Normal",
      "Flying"
    ],
    "evolution": [
      22
    ]
  },
  "22": {
    "number": 22,
    "name": "Fearow",
    "type": [
      "Normal",
      "Flying"
    ],
    "previous": 21
  },
  "23": {
    "number": 23,
    "name": "Ekans",
    "type": [
      "Poison"
    ],
    "evolution": [
      24
    ]
  },
  "24": {
    "number": 24,
    "name": "Arbok",
    "type": [
      "Poison"
    ],
    "previous": 23
  },
  "25": {
    "number": 25,
    "name": "Pikachu",
    "type": [
      "Electric"
    ],
    "evolution": [
      26
    ]
  },
  "26": {
    "number": 26,
    "name": "Raichu",
    "type": [
      "Electric"
    ],
    "previous": 25
  },
  "27": {
    "number": 27,
    "name": "Sandshrew",
    "type": [
      "Ground"
    ],
    "evolution": [
      28
    ]
  },
  "28": {
    "number": 28,
    "name": "Sandslash",
    "type": [
      "Ground"
    ],
    "previous": 27
  },
  "29": {
    "number": 29,
    "name": "Nidoran♀",
    "type": [
      "Poison"
    ],
    "evolution": [
      30,
      31
    ]
  },
  "30": {
    "number": 30,
    "name": "Nidorina",
    "type": [
      "Poison"
    ],
    "evolution": [
      31
    ],
    "previous": 29
  },
  "31": {
    "number": 31,
    "name": "Nidoqueen",
    "type": [
      "Poison",
      "Ground"
    ],
    "previous": 30
  },
  "32": {
    "number": 32,
    "name": "Nidoran♂",
    "type": [
      "Poison"
    ],
    "evolution": [
      33,
      34
    ]
  },
  "33": {
    "number": 33,
    "name": "Nidorino",
    "type": [
      "Poison"
    ],
    "evolution": [
      34
    ],
    "previous": 32
  },
  "34": {
    "number": 34,
    "name": "Nidoking",
    "type": [
      "Poison",
      "Ground"
    ],
    "previous": 33
  },
  "35": {
    "number": 35,
    "name": "Clefairy",
    "type": [
      "Fairy"
    ],
    "evolution": [
      36
    ]
  },
  "36": {
    "number": 36,
    "name": "Clefable",
    "type": [
      "Fairy"
    ],
    "previous": 35
  },
  "37": {
    "number": 37,
    "name": "Vulpix",
    "type": [
      "Fire"
    ],
    "evolution": [
      38
    ]
  },
  "38": {
    "number": 38,
    "name": "Ninetales",
    "type": [
      "Fire"
    ],
    "previous": 37
  },
  "39": {
    "number": 39,
    "name": "Jigglypuff",
    "type": [
      "Normal",
      "Fairy"
    ],
    "evolution": [
      40
    ]
  },
  "40": {
    "number": 40,
    "name": "Wigglytuff",
    "type": [
      "Normal",
      "Fairy"
    ],
    "previous": 39
  },
  "41": {
    "number": 41,
    "name": "Zubat",
    "type": [
      "Poison",
      "Flying"
    ],
    "evolution": [
      42
    ]
  },
  "42": {
    "number": 42,
    "name": "Golbat",
    "type": [
      "Poison",
      "Flying"
    ],
    "previous": 41
  },
  "43": {
    "number": 43,
    "name": "Oddish",
    "type": [
      "Grass",
      "Poison"
    ],
    "evolution": [
      44,
      45
    ]
  },
  "44": {
    "number": 44,
    "name": "Gloom",
    "type": [
      "Grass",
      "Poison"
    ],
    "evolution": [
      45
    ],
    "previous": 43
  },
  "45": {
    "number": 45,
    "name": "Vileplume",
    "type": [
      "Grass",
      "Poison"
    ],
    "previous": 44
  },
  "46": {
    "number": 46,
    "name": "Paras",
    "type": [
      "Bug",
      "Grass"
    ],
    "evolution": [
      47
    ]
  },
  "47": {
    "number": 47,
    "name": "Parasect",
    "type": [
      "Bug",
      "Grass"
    ],
    "previous": 46
  },
  "48": {
    "number": 48,
    "name": "Venonat",
    "type": [
      "Bug",
      "Poison"
    ],
    "evolution": [
      49
    ]
  },
  "49": {
    "number": 49,
    "name": "Venomoth",
    "type": [
      "Bug",
      "Poison"
    ],
    "previous": 48
  },
  "50": {
    "number": 50,
    "name": "Diglett",
    "type": [
      "Ground"
    ],
    "evolution": [
      52
    ]
  },
  "51": {
    "number": 51,
    "name": "Dugtrio",
    "type": [
      "Ground"
    ],
    "previous": 50
  },
  "52": {
    "number": 52,
    "name": "Meowth",
    "type": [
      "Normal"
    ],
    "evolution": [
      53
    ]
  },
  "53": {
    "number": 53,
    "name": "Persian",
    "type": [
      "Normal"
    ],
    "previous": 52
  },
  "54": {
    "number": 54,
    "name": "Psyduck",
    "type": [
      "Water"
    ],
    "evolution": [
      55
    ]
  },
  "55": {
    "number": 55,
    "name": "Golduck",
    "type": [
      "Water"
    ],
    "previous": 54
  },
  "56": {
    "number": 56,
    "name": "Mankey",
    "type": [
      "Fighting"
    ],
    "evolution": [
      57
    ]
  },
  "57": {
    "number": 57,
    "name": "Primeape",
    "type": [
      "Fighting"
    ],
    "previous": 56
  },
  "58": {
    "number": 58,
    "name": "Growlithe",
    "type": [
      "Fire"
    ],
    "evolution": [
      59
    ]
  },
  "59": {
    "number": 59,
    "name": "Arcanine",
    "type": [
      "Fire"
    ],
    "previous": 58
  },
  "60": {
    "number": 60,
    "name": "Poliwag",
    "type": [
      "Water"
    ],
    "evolution": [
      61,
      62
    ]
  },
  "61": {
    "number": 61,
    "name": "Poliwhirl",
    "type": [
      "Water"
    ],
    "evolution": [
      62
    ],
    "previous": 60
  },
  "62": {
    "number": 62,
    "name": "Poliwrath",
    "type": [
      "Water",
      "Fighting"
    ],
    "previous": 61
  },
  "63": {
    "number": 63,
    "name": "Abra",
    "type": [
      "Psychic"
    ],
    "evolution": [
      64,
      65
    ]
  },
  "64": {
    "number": 64,
    "name": "Kadabra",
    "type": [
      "Psychic"
    ],
    "evolution": [
      65
    ],
    "previous": 63
  },
  "65": {
    "number": 65,
    "name": "Alakazam",
    "type": [
      "Psychic"
    ],
    "previous": 64
  },
  "66": {
    "number": 66,
    "name": "Machop",
    "type": [
      "Fighting"
    ],
    "evolution": [
      67,
      68
    ]
  },
  "67": {
    "number": 67,
    "name": "Machoke",
    "type": [
      "Fighting"
    ],
    "evolution": [
      68
    ],
    "previous": 66
  },
  "68": {
    "number": 68,
    "name": "Machamp",
    "type": [
      "Fighting"
    ],
    "previous": 67
  },
  "69": {
    "number": 69,
    "name": "Bellsprout",
    "type": [
      "Grass",
      "Poison"
    ],
    "evolution": [
      70,
      71
    ]
  },
  "70": {
    "number": 7,
    "name": "Weepinbell",
    "type": [
      "Grass",
      "Poison"
    ],
    "evolution": [
      71
    ],
    "previous": 69
  },
  "71": {
    "number": 71,
    "name": "Victreebel",
    "type": [
      "Grass",
      "Poison"
    ],
    "previous": 70
  },
  "72": {
    "number": 72,
    "name": "Tentacool",
    "type": [
      "Water",
      "Poison"
    ],
    "evolution": [
      73
    ]
  },
  "73": {
    "number": 73,
    "name": "Tentacruel",
    "type": [
      "Water",
      "Poison"
    ],
    "previous": 72
  },
  "74": {
    "number": 74,
    "name": "Geodude",
    "type": [
      "Rock",
      "Ground"
    ],
    "evolution": [
      75,
      76
    ]
  },
  "75": {
    "number": 75,
    "name": "Graveler",
    "type": [
      "Rock",
      "Ground"
    ],
    "evolution": [
      76
    ],
    "previous": 74
  },
  "76": {
    "number": 76,
    "name": "Golem",
    "type": [
      "Rock",
      "Ground"
    ],
    "previous": 75
  },
  "77": {
    "number": 77,
    "name": "Ponyta",
    "type": [
      "Fire"
    ],
    "evolution": [
      78
    ]
  },
  "78": {
    "number": 78,
    "name": "Rapidash",
    "type": [
      "Fire"
    ],
    "previous": 77
  },
  "79": {
    "number": 79,
    "name": "Slowpoke",
    "type": [
      "Water",
      "Psychic"
    ],
    "evolution": [
      80
    ]
  },
  "80": {
    "number": 80,
    "name": "Slowbro",
    "type": [
      "Water",
      "Psychic"
    ],
    "previous": 79
  },
  "81": {
    "number": 81,
    "name": "Magnemite",
    "type": [
      "Electric",
      "Steel"
    ],
    "evolution": [
      82
    ]
  },
  "82": {
    "number": 82,
    "name": "Magneton",
    "type": [
      "Electric",
      "Steel"
    ],
    "previous": 81
  },
  "83": {
    "number": 83,
    "name": "Farfetch'd",
    "type": [
      "Normal",
      "Flying"
    ]
  },
  "84": {
    "number": 84,
    "name": "Doduo",
    "type": [
      "Normal",
      "Flying"
    ],
    "evolution": [
      85
    ]
  },
  "85": {
    "number": 85,
    "name": "Dodrio",
    "type": [
      "Normal",
      "Flying"
    ],
    "previous": 84
  },
  "86": {
    "number": 86,
    "name": "Seel",
    "type": [
      "Water"
    ],
    "evolution": [
      87
    ]
  },
  "87": {
    "number": 87,
    "name": "Dewgong",
    "type": [
      "Water",
      "Ice"
    ],
    "previous": 86
  },
  "88": {
    "number": 88,
    "name": "Grimer",
    "type": [
      "Poison"
    ],
    "evolution": [
      89
    ]
  },
  "89": {
    "number": 89,
    "name": "Muk",
    "type": [
      "Poison"
    ],
    "previous": 88
  },
  "90": {
    "number": 90,
    "name": "Shellder",
    "type": [
      "Water"
    ],
    "evolution": [
      91
    ]
  },
  "91": {
    "number": 91,
    "name": "Cloyster",
    "type": [
      "Water",
      "Ice"
    ],
    "previous": 90
  },
  "92": {
    "number": 92,
    "name": "Gastly",
    "type": [
      "Ghost",
      "Poison"
    ],
    "evolution": [
      93,
      94
    ]
  },
  "93": {
    "number": 93,
    "name": "Haunter",
    "type": [
      "Ghost",
      "Poison"
    ],
    "evolution": [
      94
    ],
    "previous": 92
  },
  "94": {
    "number": 94,
    "name": "Gengar",
    "type": [
      "Ghost",
      "Poison"
    ],
    "previous": 93
  },
  "95": {
    "number": 95,
    "name": "Onix",
    "type": [
      "Rock",
      "Ground"
    ]
  },
  "96": {
    "number": 96,
    "name": "Drowzee",
    "type": [
      "Psychic"
    ],
    "evolution": [
      97
    ]
  },
  "97": {
    "number": 97,
    "name": "Hypno",
    "type": [
      "Psychic"
    ],
    "previous": 96
  },
  "98": {
    "number": 98,
    "name": "Krabby",
    "type": [
      "Water"
    ],
    "evolution": [
      99
    ]
  },
  "99": {
    "number": 99,
    "name": "Kingler",
    "type": [
      "Water"
    ],
    "previous": 98
  },
  "100": {
    "number": 100,
    "name": "Voltorb",
    "type": [
      "Electric"
    ],
    "evolution": [
      101
    ]
  },
  "101": {
    "number": 101,
    "name": "Electrode",
    "type": [
      "Electric"
    ],
    "previous": 100
  },
  "102": {
    "number": 102,
    "name": "Exeggcute",
    "type": [
      "Grass",
      "Psychic"
    ],
    "evolution": [
      103
    ]
  },
  "103": {
    "number": 103,
    "name": "Exeggutor",
    "type": [
      "Grass",
      "Psychic"
    ],
    "previous": 102
  },
  "104": {
    "number": 104,
    "name": "Cubone",
    "type": [
      "Ground"
    ],
    "evolution": [
      105
    ]
  },
  "105": {
    "number": 105,
    "name": "Marowak",
    "type": [
      "Ground"
    ],
    "previous": 104
  },
  "106": {
    "number": 106,
    "name": "Hitmonlee",
    "type": [
      "Fighting"
    ]
  },
  "107": {
    "number": 107,
    "name": "Hitmonchan",
    "type": [
      "Fighting"
    ]
  },
  "108": {
    "number": 108,
    "name": "Lickitung",
    "type": [
      "Normal"
    ]
  },
  "109": {
    "number": 109,
    "name": "Koffing",
    "type": [
      "Poison"
    ],
    "evolution": [
      110
    ]
  },
  "110": {
    "number": 110,
    "name": "Weezing",
    "type": [
      "Poison"
    ],
    "previous": 109
  },
  "111": {
    "number": 111,
    "name": "Rhyhorn",
    "type": [
      "Ground",
      "Rock"
    ],
    "evolution": [
      112
    ]
  },
  "112": {
    "number": 112,
    "name": "Rhydon",
    "type": [
      "Ground",
      "Rock"
    ],
    "previous": 111
  },
  "113": {
    "number": 113,
    "name": "Chansey",
    "type": [
      "Normal"
    ]
  },
  "114": {
    "number": 114,
    "name": "Tangela",
    "type": [
      "Grass"
    ]
  },
  "115": {
    "number": 115,
    "name": "Kangaskhan",
    "type": [
      "Normal"
    ]
  },
  "116": {
    "number": 116,
    "name": "Horsea",
    "type": [
      "Water"
    ],
    "evolution": [
      117
    ]
  },
  "117": {
    "number": 117,
    "name": "Seadra",
    "type": [
      "Water"
    ],
    "previous": 116
  },
  "118": {
    "number": 118,
    "name": "Goldeen",
    "type": [
      "Water"
    ],
    "evolution": [
      119
    ]
  },
  "119": {
    "number": 119,
    "name": "Seaking",
    "type": [
      "Water"
    ],
    "previous": 118
  },
  "120": {
    "number": 120,
    "name": "Staryu",
    "type": [
      "Water"
    ],
    "evolution": [
      121
    ]
  },
  "121": {
    "number": 121,
    "name": "Starmie",
    "type": [
      "Water",
      "Psychic"
    ],
    "previous": 120
  },
  "122": {
    "number": 122,
    "name": "Mr. Mime",
    "type": [
      "Psychic",
      "Fairy"
    ]
  },
  "123": {
    "number": 123,
    "name": "Scyther",
    "type": [
      "Bug",
      "Flying"
    ]
  },
  "124": {
    "number": 124,
    "name": "Jynx",
    "type": [
      "Ice",
      "Psychic"
    ]
  },
  "125": {
    "number": 125,
    "name": "Electabuzz",
    "type": [
      "Electric"
    ]
  },
  "126": {
    "number": 126,
    "name": "Magmar",
    "type": [
      "Fire"
    ]
  },
  "127": {
    "number": 127,
    "name": "Pinsir",
    "type": [
      "Bug"
    ]
  },
  "128": {
    "number": 128,
    "name": "Tauros",
    "type": [
      "Normal"
    ]
  },
  "129": {
    "number": 129,
    "name": "Magikarp",
    "type": [
      "Water"
    ],
    "evolution": [
      130
    ]
  },
  "130": {
    "number": 130,
    "name": "Gyarados",
    "type": [
      "Water",
      "Flying"
    ],
    "previous": 129
  },
  "131": {
    "number": 131,
    "name": "Lapras",
    "type": [
      "Water",
      "Ice"
    ]
  },
  "132": {
    "number": 132,
    "name": "Ditto",
    "type": [
      "Normal"
    ]
  },
  "133": {
    "number": 133,
    "name": "Eevee",
    "type": [
      "Normal"
    ],
    "evolution": [
      134,
      135,
      136
    ]
  },
  "134": {
    "number": 134,
    "name": "Vaporeon",
    "type": [
      "Water"
    ],
    "previous": 133
  },
  "135": {
    "number": 135,
    "name": "Jolteon",
    "type": [
      "Electric"
    ],
    "previous": 133
  },
  "136": {
    "number": 136,
    "name": "Flareon",
    "type": [
      "Fire"
    ],
    "previous": 133
  },
  "137": {
    "number": 137,
    "name": "Porygon",
    "type": [
      "Normal"
    ]
  },
  "138": {
    "number": 138,
    "name": "Omanyte",
    "type": [
      "Rock",
      "Water"
    ],
    "evolution": [
      139
    ]
  },
  "139": {
    "number": 139,
    "name": "Omastar",
    "type": [
      "Rock",
      "Water"
    ],
    "previous": 138
  },
  "140": {
    "number": 140,
    "name": "Kabuto",
    "type": [
      "Rock",
      "Water"
    ],
    "evolution": [
      141
    ]
  },
  "141": {
    "number": 141,
    "name": "Kabutops",
    "type": [
      "Rock",
      "Water"
    ],
    "previous": 140
  },
  "142": {
    "number": 142,
    "name": "Aerodactyl",
    "type": [
      "Rock",
      "Flying"
    ]
  },
  "143": {
    "number": 143,
    "name": "Snorlax",
    "type": [
      "Normal"
    ]
  },
  "144": {
    "number": 144,
    "name": "Articuno",
    "type": [
      "Ice",
      "Flying"
    ]
  },
  "145": {
    "number": 145,
    "name": "Zapdos",
    "type": [
      "Electric",
      "Flying"
    ]
  },
  "146": {
    "number": 146,
    "name": "Moltres",
    "type": [
      "Fire",
      "Flying"
    ]
  },
  "147": {
    "number": 147,
    "name": "Dratini",
    "type": [
      "Dragon"
    ],
    "evolution": [
      148,
      149
    ]
  },
  "148": {
    "number": 148,
    "name": "Dragonair",
    "type": [
      "Dragon"
    ],
    "evolution": [
      149
    ],
    "previous": 147
  },
  "149": {
    "number": 149,
    "name": "Dragonite",
    "type": [
      "Dragon",
      "Flying"
    ],
    "previous": 148
  },
  "150": {
    "number": 150,
    "name": "Mewtwo",
    "type": [
      "Psychic"
    ]
  },
  "151": {
    "number": 151,
    "name": "Mew",
    "type": [
      "Psychic"
    ]
  }
}